sunday/__init__.py
sv_sunday-0.1.0.dist-info/METADATA
sv_sunday-0.1.0.dist-info/WHEEL
sv_sunday-0.1.0.dist-info/RECORD
