Metadata-Version: 2.4
Name: sv-sunday
Version: 0.1.0
Summary: Let us code on sunday
Requires-Python: >=3.12
Requires-Dist: svlearn-bootcamp>=0.1.7
